.gitignore
.hgignore
README.rst
monkeypatch.py
setup.py
monkeypatch.egg-info/PKG-INFO
monkeypatch.egg-info/SOURCES.txt
monkeypatch.egg-info/dependency_links.txt
monkeypatch.egg-info/namespace_packages.txt
monkeypatch.egg-info/top_level.txt
monkeypatch.egg-info/zip-safe