Metadata-Version: 1.0
Name: monkeypatch
Version: 0.1rc3
Summary: Monkey patcher
Home-page: https://github.com/iki/monkeypatch
Author: Jan Killian
Author-email: jan.killian@gmail.com
License: BSD
Keywords: patch,monkey-patch
Platform: any
Classifier: Development Status :: 4 - Beta
Classifier: Intended Audience :: Developers
Classifier: License :: OSI Approved :: BSD License
Classifier: Operating System :: OS Independent
Classifier: Programming Language :: Python
Classifier: Topic :: Software Development :: Libraries :: Python Modules
